ipetsc/__main__.py
ipetsc-2023.0.dist-info/LICENSE.txt
ipetsc-2023.0.dist-info/METADATA
ipetsc-2023.0.dist-info/WHEEL
ipetsc-2023.0.dist-info/entry_points.txt
ipetsc-2023.0.dist-info/RECORD
